vhdl-designs/comb/led/counter.vhd
library ieee;
use ieee.std_logic_1164.all;
use ieee.std_logic_unsigned.all;

entity counter is
	port (
		clk, reset: in std_logic;
		count: out std_logic_vector (3 downto 0)
	);
end entity;

architecture behavior of counter is
begin
	process(clk, reset)
	begin
		if reset = '1' then
			count <= "0000";
		elsif rising_edge(clk) then
			if count = "1001" then
				count <= "0000";
			else 
				count <= count + 1;
			end if;
		end if;
	end process;
end architecture;

TeX-Files/vhdl_codes/LED_Counter/led_decoder.vhd
library ieee;
use ieee.std_logic_1164.all;
use ieee.std_logic_unsigned.all;
use ieee.std_logic_arith.ALL;

entity led_decoder is
    port ( 
        clk : in std_logic;
        d   : in  std_logic_vector (3 downto 0);
        s   : out std_logic_vector (6 downto 0)
    );
end entity;

architecture behavior of led_decoder is
begin
    DUT: process(clk, d)
    begin
        if rising_edge(clk) then
            s<="1110111" when d="0000" else
            "0010010" when d="0001" else
            "1011101" when d="0010" else
            "1011011" when d="0011" else
            "0111010" when d="0100" else
            "1101011" when d="0101" else
            "1101111" when d="0110" else
            "1010010" when d="0111" else
            "1111111" when d="1000" else
            "1111011" when d="1001" else
            "1111110" when d="1010" else
            "0101111" when d="1011" else
            "1100101" when d="1100" else
            "0011111" when d="1101" else
            "1101101" when d="1110" else
            "1101100";
        end if;
    end process;
end architecture;

vhdl files/comb/led/led_counter.vhd
library ieee;
use ieee.std_logic_1164.all;

entity led_counter is
	port (
		clk, reset: in std_logic;
		Q_out: out std_logic_vector (6 downto 0)
	);
end entity;

architecture behavior of led_counter is
  signal counter_value : std_logic_vector (3 downto 0);
begin
  LED: entity work.led_decoder port map (clk, counter_value, Q_out);
  COUNT: entity work.counter port map (clk, reset, counter_value);
end architecture;

vhdl files/seq/led/tb_led_counter.vhd
library ieee;
use ieee.std_logic_1164.all;
use std.env.finish;

entity tb_led_counter is
end entity;

architecture behavior of tb_led_counter is
    constant clk_period: time := 10 ns;

    signal clk: std_logic := '0';
    signal reset: std_logic := '0';
    signal led: std_logic_vector(6 downto 0) := "0000000";
begin
	UUT: entity work.led_counter port map(clk, reset, led);

	clk_process : process
	begin
		clk <= '0';
		wait for clk_period/2;
		clk <= '1';
		wait for clk_period/2;
	end process;

	stimulus : process
	begin
		reset <= '1';
		wait for 100 ns;
		reset <= '0';
		wait for 100 ns;
		reset <= '1';
		wait for 50 ns;
		reset <= '0';
		wait for 450 ns;
		finish;
	end process;
end architecture;

vhdl files/seq/led/tb_led_counter.vcd
$date
  Mon Jan 15 12:36:10 2024
$end
$version
  GHDL v0
$end
$timescale
  1 fs
$end
$scope module standard $end
$upscope $end
$scope module textio $end
$upscope $end
$scope module std_logic_1164 $end
$upscope $end
$scope module env $end
$upscope $end
$scope module std_logic_arith $end
$upscope $end
$scope module std_logic_unsigned $end
$upscope $end
$scope module tb_led_counter $end
$var reg 1 ! clk $end
$var reg 1 " reset $end
$var reg 7 # led[6:0] $end
$scope module uut $end
$var reg 1 $ clk $end
$var reg 1 % reset $end
$var reg 7 & q_out[6:0] $end
$var reg 4 ' counter_value[3:0] $end
$scope module led $end
$var reg 1 ( clk $end
$var reg 4 ) d[3:0] $end
$var reg 7 * s[6:0] $end
$upscope $end
$scope module count $end
$var reg 1 + clk $end
$var reg 1 , reset $end
$var reg 4 - count[3:0] $end
$upscope $end
$upscope $end
$upscope $end
$enddefinitions $end
#0
0!
1"
bUUUUUUU #
0$
1%
bUUUUUUU &
b0000 '
0(
b0000 )
bUUUUUUU *
0+
1,
b0000 -
#5000000
1!
b1110111 #
1$
b1110111 &
1(
b1110111 *
1+
#10000000
0!
0$
0(
0+
#15000000
1!
1$
1(
1+
#20000000
0!
0$
0(
0+
#25000000
1!
1$
1(
1+
#30000000
0!
0$
0(
0+
#35000000
1!
1$
1(
1+
#40000000
0!
0$
0(
0+
#45000000
1!
1$
1(
1+
#50000000
0!
0$
0(
0+
#55000000
1!
1$
1(
1+
#60000000
0!
0$
0(
0+
#65000000
1!
1$
1(
1+
#70000000
0!
0$
0(
0+
#75000000
1!
1$
1(
1+
#80000000
0!
0$
0(
0+
#85000000
1!
1$
1(
1+
#90000000
0!
0$
0(
0+
#95000000
1!
1$
1(
1+
#100000000
0!
0"
0$
0%
0(
0+
0,
#105000000
1!
1$
b0001 '
1(
b0001 )
1+
b0001 -
#110000000
0!
0$
0(
0+
#115000000
1!
b0010010 #
1$
b0010010 &
b0010 '
1(
b0010 )
b0010010 *
1+
b0010 -
#120000000
0!
0$
0(
0+
#125000000
1!
b1011101 #
1$
b1011101 &
b0011 '
1(
b0011 )
b1011101 *
1+
b0011 -
#130000000
0!
0$
0(
0+
#135000000
1!
b1011011 #
1$
b1011011 &
b0100 '
1(
b0100 )
b1011011 *
1+
b0100 -
#140000000
0!
0$
0(
0+
#145000000
1!
b0111010 #
1$
b0111010 &
b0101 '
1(
b0101 )
b0111010 *
1+
b0101 -
#150000000
0!
0$
0(
0+
#155000000
1!
b1101011 #
1$
b1101011 &
b0110 '
1(
b0110 )
b1101011 *
1+
b0110 -
#160000000
0!
0$
0(
0+
#165000000
1!
b1101111 #
1$
b1101111 &
b0111 '
1(
b0111 )
b1101111 *
1+
b0111 -
#170000000
0!
0$
0(
0+
#175000000
1!
b1010010 #
1$
b1010010 &
b1000 '
1(
b1000 )
b1010010 *
1+
b1000 -
#180000000
0!
0$
0(
0+
#185000000
1!
b1111111 #
1$
b1111111 &
b1001 '
1(
b1001 )
b1111111 *
1+
b1001 -
#190000000
0!
0$
0(
0+
#195000000
1!
b1111011 #
1$
b1111011 &
b0000 '
1(
b0000 )
b1111011 *
1+
b0000 -
#200000000
0!
1"
0$
1%
0(
0+
1,
#205000000
1!
b1110111 #
1$
b1110111 &
1(
b1110111 *
1+
#210000000
0!
0$
0(
0+
#215000000
1!
1$
1(
1+
#220000000
0!
0$
0(
0+
#225000000
1!
1$
1(
1+
#230000000
0!
0$
0(
0+
#235000000
1!
1$
1(
1+
#240000000
0!
0$
0(
0+
#245000000
1!
1$
1(
1+
#250000000
0!
0"
0$
0%
0(
0+
0,
#255000000
1!
1$
b0001 '
1(
b0001 )
1+
b0001 -
#260000000
0!
0$
0(
0+
#265000000
1!
b0010010 #
1$
b0010010 &
b0010 '
1(
b0010 )
b0010010 *
1+
b0010 -
#270000000
0!
0$
0(
0+
#275000000
1!
b1011101 #
1$
b1011101 &
b0011 '
1(
b0011 )
b1011101 *
1+
b0011 -
#280000000
0!
0$
0(
0+
#285000000
1!
b1011011 #
1$
b1011011 &
b0100 '
1(
b0100 )
b1011011 *
1+
b0100 -
#290000000
0!
0$
0(
0+
#295000000
1!
b0111010 #
1$
b0111010 &
b0101 '
1(
b0101 )
b0111010 *
1+
b0101 -
#300000000
0!
0$
0(
0+
#305000000
1!
b1101011 #
1$
b1101011 &
b0110 '
1(
b0110 )
b1101011 *
1+
b0110 -
#310000000
0!
0$
0(
0+
#315000000
1!
b1101111 #
1$
b1101111 &
b0111 '
1(
b0111 )
b1101111 *
1+
b0111 -
#320000000
0!
0$
0(
0+
#325000000
1!
b1010010 #
1$
b1010010 &
b1000 '
1(
b1000 )
b1010010 *
1+
b1000 -
#330000000
0!
0$
0(
0+
#335000000
1!
b1111111 #
1$
b1111111 &
b1001 '
1(
b1001 )
b1111111 *
1+
b1001 -
#340000000
0!
0$
0(
0+
#345000000
1!
b1111011 #
1$
b1111011 &
b0000 '
1(
b0000 )
b1111011 *
1+
b0000 -
#350000000
0!
0$
0(
0+
#355000000
1!
b1110111 #
1$
b1110111 &
b0001 '
1(
b0001 )
b1110111 *
1+
b0001 -
#360000000
0!
0$
0(
0+
#365000000
1!
b0010010 #
1$
b0010010 &
b0010 '
1(
b0010 )
b0010010 *
1+
b0010 -
#370000000
0!
0$
0(
0+
#375000000
1!
b1011101 #
1$
b1011101 &
b0011 '
1(
b0011 )
b1011101 *
1+
b0011 -
#380000000
0!
0$
0(
0+
#385000000
1!
b1011011 #
1$
b1011011 &
b0100 '
1(
b0100 )
b1011011 *
1+
b0100 -
#390000000
0!
0$
0(
0+
#395000000
1!
b0111010 #
1$
b0111010 &
b0101 '
1(
b0101 )
b0111010 *
1+
b0101 -
#400000000
0!
0$
0(
0+
#405000000
1!
b1101011 #
1$
b1101011 &
b0110 '
1(
b0110 )
b1101011 *
1+
b0110 -
#410000000
0!
0$
0(
0+
#415000000
1!
b1101111 #
1$
b1101111 &
b0111 '
1(
b0111 )
b1101111 *
1+
b0111 -
#420000000
0!
0$
0(
0+
#425000000
1!
b1010010 #
1$
b1010010 &
b1000 '
1(
b1000 )
b1010010 *
1+
b1000 -
#430000000
0!
0$
0(
0+
#435000000
1!
b1111111 #
1$
b1111111 &
b1001 '
1(
b1001 )
b1111111 *
1+
b1001 -
#440000000
0!
0$
0(
0+
#445000000
1!
b1111011 #
1$
b1111011 &
b0000 '
1(
b0000 )
b1111011 *
1+
b0000 -
#450000000
0!
0$
0(
0+
#455000000
1!
b1110111 #
1$
b1110111 &
b0001 '
1(
b0001 )
b1110111 *
1+
b0001 -
#460000000
0!
0$
0(
0+
#465000000
1!
b0010010 #
1$
b0010010 &
b0010 '
1(
b0010 )
b0010010 *
1+
b0010 -
#470000000
0!
0$
0(
0+
#475000000
1!
b1011101 #
1$
b1011101 &
b0011 '
1(
b0011 )
b1011101 *
1+
b0011 -
#480000000
0!
0$
0(
0+
#485000000
1!
b1011011 #
1$
b1011011 &
b0100 '
1(
b0100 )
b1011011 *
1+
b0100 -
#490000000
0!
0$
0(
0+
#495000000
1!
b0111010 #
1$
b0111010 &
b0101 '
1(
b0101 )
b0111010 *
1+
b0101 -
#500000000
0!
0$
0(
0+
#505000000
1!
b1101011 #
1$
b1101011 &
b0110 '
1(
b0110 )
b1101011 *
1+
b0110 -
#510000000
0!
0$
0(
0+
#515000000
1!
b1101111 #
1$
b1101111 &
b0111 '
1(
b0111 )
b1101111 *
1+
b0111 -
#520000000
0!
0$
0(
0+
#525000000
1!
b1010010 #
1$
b1010010 &
b1000 '
1(
b1000 )
b1010010 *
1+
b1000 -
#530000000
0!
0$
0(
0+
#535000000
1!
b1111111 #
1$
b1111111 &
b1001 '
1(
b1001 )
b1111111 *
1+
b1001 -
#540000000
0!
0$
0(
0+
#545000000
1!
b1111011 #
1$
b1111011 &
b0000 '
1(
b0000 )
b1111011 *
1+
b0000 -
#550000000
0!
0$
0(
0+
#555000000
1!
b1110111 #
1$
b1110111 &
b0001 '
1(
b0001 )
b1110111 *
1+
b0001 -
#560000000
0!
0$
0(
0+
#565000000
1!
b0010010 #
1$
b0010010 &
b0010 '
1(
b0010 )
b0010010 *
1+
b0010 -
#570000000
0!
0$
0(
0+
#575000000
1!
b1011101 #
1$
b1011101 &
b0011 '
1(
b0011 )
b1011101 *
1+
b0011 -
#580000000
0!
0$
0(
0+
#585000000
1!
b1011011 #
1$
b1011011 &
b0100 '
1(
b0100 )
b1011011 *
1+
b0100 -
#590000000
0!
0$
0(
0+
#595000000
1!
b0111010 #
1$
b0111010 &
b0101 '
1(
b0101 )
b0111010 *
1+
b0101 -
#600000000
0!
0$
0(
0+
#605000000
1!
b1101011 #
1$
b1101011 &
b0110 '
1(
b0110 )
b1101011 *
1+
b0110 -
#610000000
0!
0$
0(
0+
#615000000
1!
b1101111 #
1$
b1101111 &
b0111 '
1(
b0111 )
b1101111 *
1+
b0111 -
#620000000
0!
0$
0(
0+
#625000000
1!
b1010010 #
1$
b1010010 &
b1000 '
1(
b1000 )
b1010010 *
1+
b1000 -
#630000000
0!
0$
0(
0+
#635000000
1!
b1111111 #
1$
b1111111 &
b1001 '
1(
b1001 )
b1111111 *
1+
b1001 -
#640000000
0!
0$
0(
0+
#645000000
1!
b1111011 #
1$
b1111011 &
b0000 '
1(
b0000 )
b1111011 *
1+
b0000 -
#650000000
0!
0$
0(
0+
#655000000
1!
b1110111 #
1$
b1110111 &
b0001 '
1(
b0001 )
b1110111 *
1+
b0001 -
#660000000
0!
0$
0(
0+
#665000000
1!
b0010010 #
1$
b0010010 &
b0010 '
1(
b0010 )
b0010010 *
1+
b0010 -
#670000000
0!
0$
0(
0+
#675000000
1!
b1011101 #
1$
b1011101 &
b0011 '
1(
b0011 )
b1011101 *
1+
b0011 -
#680000000
0!
0$
0(
0+
#685000000
1!
b1011011 #
1$
b1011011 &
b0100 '
1(
b0100 )
b1011011 *
1+
b0100 -
#690000000
0!
0$
0(
0+
#695000000
1!
b0111010 #
1$
b0111010 &
b0101 '
1(
b0101 )
b0111010 *
1+
b0101 -
