vhdl files/seq/mult/full_adder.vhd
library ieee;
use ieee.std_logic_1164.all;

entity full_adder is
  port (
    x_in, y_in, c_in : in  std_logic;
    s_out, c_out     : out std_logic
  );
end entity;

architecture behavior of full_adder is
begin
  DUT : process(x_in, y_in, c_in)
  begin
    s_out <= x_in xor y_in xor c_in;
    c_out <= (x_in and y_in) or (x_in and c_in) or (y_in and c_in);
  end process;
end architecture;

vhdl files/comb/fa/tb_full_adder.vhd
library ieee;
use ieee.std_logic_1164.all;
use ieee.std_logic_textio.all;

library STD;
use STD.textio.all;

entity tb_full_adder is
end entity;

architecture bench of tb_full_adder is
  signal x_tb_in  : std_logic;
  signal y_tb_in  : std_logic;
  signal c_tb_in  : std_logic;
  signal s_tb_out : std_logic;
  signal c_tb_out : std_logic;

begin
  DUT: entity work.full_adder port map(x_tb_in, y_tb_in, c_tb_in, s_tb_out, c_tb_out);
  process

    file Fin : text open read_mode is "full_adder_input.txt";

    variable current_read_line   : line;
    variable current_read_field1 : std_logic;
    variable current_read_field2 : std_logic;
    variable current_read_field3 : std_logic;
    variable current_read_field4 : std_logic;
    variable current_read_field5 : std_logic;

  begin
    while (not endFile(Fin)) loop

      readline(Fin, current_read_line);
      read(current_read_line, current_read_field1);
      read(current_read_line, current_read_field2);
      read(current_read_line, current_read_field3);
      read(current_read_line, current_read_field4);
      read(current_read_line, current_read_field5);

      x_tb_in <= current_read_field1;
      y_tb_in <= current_read_field2;
      c_tb_in <= current_read_field3;

      wait for 50 ns;

      assert(c_tb_out = current_read_field4) report "Error in carry" severity failure;
      assert(s_tb_out = current_read_field5) report "Error in sum" severity failure;
    end loop;
    wait;
  end process;
end architecture;

vhdl files/comb/fa/tb_full_adder.vcd
$date
  Mon Jan 15 03:18:29 2024
$end
$version
  GHDL v0
$end
$timescale
  1 fs
$end
$scope module standard $end
$upscope $end
$scope module textio $end
$upscope $end
$scope module std_logic_1164 $end
$upscope $end
$scope module std_logic_textio $end
$upscope $end
$scope module tb_full_adder $end
$var reg 1 ! x_tb_in $end
$var reg 1 " y_tb_in $end
$var reg 1 # c_tb_in $end
$var reg 1 $ s_tb_out $end
$var reg 1 % c_tb_out $end
$scope module dut $end
$var reg 1 & x_in $end
$var reg 1 ' y_in $end
$var reg 1 ( c_in $end
$var reg 1 ) s_out $end
$var reg 1 * c_out $end
$upscope $end
$upscope $end
$enddefinitions $end
#0
0!
0"
0#
0$
0%
0&
0'
0(
0)
0*
#50000000
1#
1$
1(
1)
#100000000
1"
0#
1'
0(
#150000000
1#
0$
1%
1(
0)
1*
#200000000
1!
0"
0#
1$
0%
1&
0'
0(
1)
0*
#250000000
1#
0$
1%
1(
0)
1*
#300000000
1"
0#
1'
0(
#350000000
1#
1$
1(
1)
