vhdl files/comb/enc/encoder_16to4.vhd
library ieee;
use ieee.std_logic_1164.all;

entity encoder_16to4 is
  port (
    D_in: in std_logic_vector(15 downto 0);
    Q_out: out std_logic_vector(3 downto 0)
  );
end entity;

architecture behavior of encoder_16to4 is
begin
  DUT: process(D_in)
  begin
    case D_in is
      when "0000000000000001" => Q_out <= "0000";
      when "0000000000000010" => Q_out <= "0001";
      when "0000000000000100" => Q_out <= "0010";
      when "0000000000001000" => Q_out <= "0011";
      when "0000000000010000" => Q_out <= "0100";
      when "0000000000100000" => Q_out <= "0101";
      when "0000000001000000" => Q_out <= "0110";
      when "0000000010000000" => Q_out <= "0111";
      when "0000000100000000" => Q_out <= "1000";
      when "0000001000000000" => Q_out <= "1001";
      when "0000010000000000" => Q_out <= "1010";
      when "0000100000000000" => Q_out <= "1011";
      when "0001000000000000" => Q_out <= "1100";
      when "0010000000000000" => Q_out <= "1101";
      when "0100000000000000" => Q_out <= "1110";
      when "1000000000000000" => Q_out <= "1111";
      when others => Q_out <= "XXXX";
    end case;   
  end process;
end architecture;

vhdl files/comb/enc/tb_encoder_16to4.vhd
library ieee;
use ieee.std_logic_1164.all;
use ieee.std_logic_textio.all;

library STD;
use STD.textio.all;

entity tb_encoder_16to4 is
end entity;

architecture behavior of tb_encoder_16to4 is
  signal D_tb_in: std_logic_vector(15 downto 0);
  signal Q_tb_out: std_logic_vector(3 downto 0);
begin
  DUT: entity work.encoder_16to4 port map (D_tb_in, Q_tb_out);
  process
    file f_in: text open read_mode is "encoder_16to4_test.txt";
    
    variable current_read_line: line;
    variable current_read_field1: std_logic_vector(0 to 15);
    variable current_read_field2: std_logic_vector(0 to 3);
  begin
    while (not endFile(f_in)) loop
      readline(f_in, current_read_line);
      read(current_read_line, current_read_field1);
      read(current_read_line, current_read_field2);

      D_tb_in<= current_read_field1;
      wait for 50 ns;

      assert(Q_tb_out = current_read_field2);
    end loop;
    wait;
  end process;
end architecture;

vhdl-designs/comb/enc/tb_encoder_16to4.vcd
$date
  Mon Jan 15 03:28:54 2024
$end
$version
  GHDL v0
$end
$timescale
  1 fs
$end
$scope module standard $end
$upscope $end
$scope module textio $end
$upscope $end
$scope module std_logic_1164 $end
$upscope $end
$scope module std_logic_textio $end
$upscope $end
$scope module tb_encoder_16to4 $end
$var reg 16 ! d_tb_in[15:0] $end
$var reg 4 " q_tb_out[3:0] $end
$scope module dut $end
$var reg 16 # d_in[15:0] $end
$var reg 4 $ q_out[3:0] $end
$upscope $end
$upscope $end
$enddefinitions $end
#0
b0000000000000001 !
b0000 "
b0000000000000001 #
b0000 $
#50000000
b0000000000000010 !
b0001 "
b0000000000000010 #
b0001 $
#100000000
b0000000000000100 !
b0010 "
b0000000000000100 #
b0010 $
#150000000
b0000000000001000 !
b0011 "
b0000000000001000 #
b0011 $
#200000000
b0000000000010000 !
b0100 "
b0000000000010000 #
b0100 $
#250000000
b0000000000100000 !
b0101 "
b0000000000100000 #
b0101 $
#300000000
b0000000001000000 !
b0110 "
b0000000001000000 #
b0110 $
#350000000
b0000000010000000 !
b0111 "
b0000000010000000 #
b0111 $
#400000000
b0000000100000000 !
b1000 "
b0000000100000000 #
b1000 $
#450000000
b0000001000000000 !
b1001 "
b0000001000000000 #
b1001 $
#500000000
b0000010000000000 !
b1010 "
b0000010000000000 #
b1010 $
#550000000
b0000100000000000 !
b1011 "
b0000100000000000 #
b1011 $
#600000000
b0001000000000000 !
b1100 "
b0001000000000000 #
b1100 $
#650000000
b0010000000000000 !
b1101 "
b0010000000000000 #
b1101 $
#700000000
b0100000000000000 !
b1110 "
b0100000000000000 #
b1110 $
#750000000
b1000000000000000 !
b1111 "
b1000000000000000 #
b1111 $
