vhdl files/seq/jkff/jk_flip_flop.vhd
library ieee;
use ieee.std_logic_1164.all;

entity jk_flip_flop is
	port ( 
		J_in: in  std_logic;
		K_in: in  std_logic;
		rst, clk: in  std_logic;
		Q_out: inout std_logic
	);
end entity;

architecture behavior of jk_flip_flop is
begin
	DUT: process (rst, clk) is
	begin
		if rst = '1' then 
			Q_out <= '0';
		elsif(rising_edge(clk)) then
			if (J_in = '0' and K_in = '0') then
				Q_out <= Q_out;
			elsif (J_in = '0' and K_in = '1') then
				Q_out <= '0';
			elsif (J_in = '1' and K_in = '0') then
				Q_out <= '1';
			elsif (J_in = '1' and K_in = '1') then
				Q_out <= not (Q_out);
			end if;
		end if;
	end process;
end behavior;

vhdl files/seq/jkff/tb_jk_flip_flop.vhd
library ieee;
use ieee.std_logic_1164.all;
use std.env.finish;

entity tb_jk_flip_flop is
end entity;

architecture behavior of tb_jk_flip_flop is
	signal J_tb_in: std_logic := '0';
	signal K_tb_in: std_logic := '0';
	signal rst_n_tb: std_logic := '0';
	signal clk_tb: std_logic := '0';
	signal Q_tb_out: std_logic;

	constant clk_period : time := 10 ns;

begin
	UUT: entity work.jk_flip_flop port map (J_tb_in, K_tb_in, rst_n_tb, clk_tb, Q_tb_out);

	clk_process : process
	begin
		clk_tb <= '0';
		wait for clk_period/2;
		clk_tb <= '1';
		wait for clk_period/2;
	end process;

	stimulus: process
	begin
		J_tb_in <= '1';
		K_tb_in <= '0';
		rst_n_tb <= '0';
		wait for 20 ns;
		assert(Q_tb_out = '1') report "Error in q" severity failure;

		J_tb_in <= '0';
		K_tb_in <= '0';
		rst_n_tb <= '0';
		wait for 20 ns;
		assert(Q_tb_out = '1') report "Error in q" severity failure;

		J_tb_in <= '0';
		K_tb_in <= '1';
		rst_n_tb <= '0';
		wait for 20 ns;
		assert(Q_tb_out = '0') report "Error in q" severity failure;

		J_tb_in <= '1';
		K_tb_in <= '1';
		rst_n_tb <= '0';
		wait for 20 ns;
		assert(Q_tb_out = '0') report "Error in q" severity failure;

		J_tb_in <= '1';
		K_tb_in <= '1';
		rst_n_tb <= '1';
		wait for 20 ns;
		assert(Q_tb_out = '0') report "Error in q" severity failure;
		
		finish;
	end process;
end architecture;

vhdl files/seq/jkff/tb_jk_flip_flop.vcd
$date
  Mon Jan 15 03:59:18 2024
$end
$version
  GHDL v0
$end
$timescale
  1 fs
$end
$scope module standard $end
$upscope $end
$scope module textio $end
$upscope $end
$scope module std_logic_1164 $end
$upscope $end
$scope module env $end
$upscope $end
$scope module tb_jk_flip_flop $end
$var reg 1 ! j_tb_in $end
$var reg 1 " k_tb_in $end
$var reg 1 # rst_n_tb $end
$var reg 1 $ clk_tb $end
$var reg 1 % q_tb_out $end
$scope module uut $end
$var reg 1 & j_in $end
$var reg 1 ' k_in $end
$var reg 1 ( rst $end
$var reg 1 ) clk $end
$var reg 1 * q_out $end
$upscope $end
$upscope $end
$enddefinitions $end
#0
1!
0"
0#
0$
U%
1&
0'
0(
0)
U*
#5000000
1$
1%
1)
1*
#10000000
0$
0)
#15000000
1$
1)
#20000000
0!
0$
0&
0)
#25000000
1$
1)
#30000000
0$
0)
#35000000
1$
1)
#40000000
1"
0$
1'
0)
#45000000
1$
0%
1)
0*
#50000000
0$
0)
#55000000
1$
1)
#60000000
1!
0$
1&
0)
#65000000
1$
1%
1)
1*
#70000000
0$
0)
#75000000
1$
0%
1)
0*
#80000000
1#
0$
1(
0)
