vhdl files/seq/mult/n_register.vhd
library IEEE;
use IEEE.STD_LOGIC_1164.ALL;

-- N-bit Register
-- E = '1', clear = '0' --> Input data 'D' is copied on Q
-- E = '1', clear = '1' --> Q is cleared (0)
entity n_register is
   	generic (N: INTEGER:= 4);
	port ( 
		clk, reset	: in std_logic;
	    E, clear	: in std_logic; -- clear: Synchronous clear
		D			: in std_logic_vector (N-1 downto 0);
	    Q			: out std_logic_vector (N-1 downto 0));
end n_register;

architecture Behavioral of n_register is
	signal Qt		: std_logic_vector (N-1 downto 0);
begin
	process (reset, clk)
	begin
		if reset = '0' then
			Qt <= (others => '0');
		elsif (clk'event and clk = '1') then
			if E = '1' then	
				if clear = '1' then
					Qt <= (others => '0');
				else
					Qt <= D;
				end if;
			end if;
		end if;
	end process;
	Q <= Qt;
end Behavioral;

vhdl-designs/comb/fa/full_adder.vhd
library ieee;
use ieee.std_logic_1164.all;

entity full_adder is
  port (
    x_in, y_in, c_in : in  std_logic;
    s_out, c_out     : out std_logic
  );
end entity;

architecture behavior of full_adder is
begin
  DUT: process(x_in, y_in, c_in)
  begin
    s_out <= x_in xor y_in xor c_in;
    c_out <= (x_in and y_in) or (x_in and c_in) or (y_in and c_in);
  end process;
end architecture;

vhdl-designs/seq/mult/add_sub.vhd
library IEEE;
use IEEE.STD_LOGIC_1164.ALL;

entity add_sub is
	generic (N: INTEGER:= 4);
	port(
		addsub: in std_logic; -- addsub = 0 (add), addsub = 1 (sub)
		x, y: in std_logic_vector (N-1 downto 0);
		s: out std_logic_vector (N-1 downto 0);
		overflow: out std_logic;
		cout: out std_logic);
end add_sub;

architecture structure of add_sub is
	component full_adder
		port( 
			x_in, y_in, c_in : in  std_logic;
    		s_out, c_out: out std_logic
		);
	end component;

	signal c: std_logic_vector (N downto 0);
	signal yx: std_logic_vector (N-1 downto 0);
begin
   	c(0) <= addsub; 
	cout <= c(N);
	overflow <= c(N) xor c(N-1);	

	gi: for i in 0 to N-1 generate
			yx(i) <= y(i) xor addsub;
			fi: full_adder port map (
				c_in => c(i), x_in => x(i), y_in => yx(i), s_out => s(i), 
				c_out => c(i+1)
			);
	    end generate;
end structure;

vhdl files/seq/mult/parallel_shift_reg.vhd
library IEEE;
use IEEE.STD_LOGIC_1164.ALL;

-- N-bit Parallel access Shift register:
-- DIR = "LEFT" --> Shift to the left: from LSB to MSB
-- DIR = "RIGHT" --> Shift to the right: from MSB to LSB
-- s_l = 0 --> Shift operation (MSB to LSB)
-- s_l = 1 -> Parallel load
entity parallel_shift_reg is
   	generic (
		N	: INTEGER	:= 4;
	    DIR	: STRING	:= "LEFT"
	);

	port ( 
		clk, reset	: in std_logic;
	    din, E, s_l	: in std_logic; -- din: shiftin input
		D			: in std_logic_vector (N-1 downto 0);
	    Q			: out std_logic_vector (N-1 downto 0);
        shift_out	: out std_logic
	);
end parallel_shift_reg;

architecture Behavioral of parallel_shift_reg is
	signal Qt: std_logic_vector (N-1 downto 0);
begin

a0: assert (DIR = "LEFT" or DIR = "RIGHT")
    report "DIR can only be LEFT or RIGHT" severity error;
	
	process (reset, clk)
	begin
		if reset = '0' then
			Qt <= (others => '0');
		elsif (clk'event and clk = '1') then
			if E = '1' then	
				if s_l = '1' then
					Qt <= D;					
				else
					if DIR = "LEFT" then
						Qt(0) <= din;
						for i in 1 to N-1 loop
							Qt(i) <= Qt(i-1);
						end loop;
					elsif DIR = "RIGHT" then
						Qt(N-1) <= din;
						for i in 0 to N-2 loop
							Qt(i) <= Qt(i+1);
						end loop;
					end if;
				end if;
			end if;
		end if;
		
	end process;

	Q <= Qt;
	
	gl: if DIR = "LEFT" generate
			shift_out <= Qt(N-1);
		end generate;
	gr: if DIR = "RIGHT" generate
			shift_out <= Qt(0);
		end generate;		
end Behavioral;

vhdl-designs/seq/mult/multiplier.vhd
library IEEE;
use IEEE.STD_LOGIC_1164.ALL;

entity multiplier is
	generic (N: INTEGER	:= 4);
	port (
		clk, reset, s: in std_logic;
		dA, dB: in std_logic_vector (N-1 downto 0);
		P: out std_logic_vector (2*N-1 downto 0);
		done: out std_logic
	);
end multiplier;

architecture Behavioral of multiplier is
	component parallel_shift_reg
		generic (
			N: INTEGER := 4;
			DIR: STRING := "LEFT"
		);
		port ( 
			clk, reset: in std_logic;
			din, E, s_l: in std_logic; --din: shiftin input
			D: in std_logic_vector (N-1 downto 0);
			Q: out std_logic_vector (N-1 downto 0);
			shift_out: out std_logic
		);
	end component;
	
	component add_sub
		generic (N: INTEGER := 4);
		port(	
			addsub: in std_logic;
			x, y: in std_logic_vector (N-1 downto 0);
			s: out std_logic_vector (N-1 downto 0);
			overflow, cout: out std_logic
		);
	end component;
	
	component n_register
		generic (N: INTEGER := 4);
		port ( 
			clk, reset: in std_logic;
			E, clear: in std_logic; -- clear: Synchronous clear
			D: in std_logic_vector (N-1 downto 0);
			Q: out std_logic_vector (N-1 downto 0)
		);
	end component;

	type state is (S1, S2, S3);
	signal y: state;
	
	signal L, E, EP, sclrP, z: std_logic;
	signal B: std_logic_vector (N-1 downto 0);
	signal A, dAx, dP, Pt: std_logic_vector (2*N -1 downto 0);

begin
rA: parallel_shift_reg generic map (N => 2*N, DIR => "LEFT")
    port map (
		clk => clk, reset => reset, din => '0', 
		s_l => L, E => E, D => dAx, Q => A
	);
	dAx (2*N-1 downto N)<= (others =>'0');
	dAx (N-1 downto 0)	<= dA;

rB: parallel_shift_reg generic map (N => N, DIR => "RIGHT")
    port map (
		clk => clk, reset => reset, din => '0',
		s_l => L, E => E, D => dB, Q => B
	);
	 
-- n-bit NOR gate:
	process (B)
		variable result_or: std_logic;
	begin
		result_or := '0';
		for i in B'range loop -- 'range: iterates through all bits in 'A'
			result_or := result_or or B(i);
		end loop;		
		z <= not (result_or);
	end process;
	 
--Adder:
ga: add_sub generic map (N => 2*N)
    port map (addsub => '0', x => A, y => Pt, s => dP);
	 
--Register P:
rP: n_register generic map (N => 2*N)
	port map (
		clk => clk, reset => reset, E => EP,
	  	clear => sclrP, D => dP, Q => Pt
	);
	P <= Pt;

--FSM:
	Transitions: process (reset, clk, s, z, B(0))
	begin
	if reset = '0' then -- asynchronous signal
		y <= S1; 		-- if reset asserted, go to initial state: S1			
	elsif (clk'event and clk = '1') then
		case y is
			when S1 => if s = '1' then y <= S2; else y <= S1; end if;
			when S2 => if z = '1' then y <= S3; else y <= S2; end if;
			when S3 => if s = '1' then y <= S3; else y <= S1; end if;
		end case;
	end if;
	end process;
	
	Outputs: process (y, s, z, B(0))
	begin
--Initialization of output signals
	sclrP <= '0'; EP <= '0'; L <= '0'; E <= '0'; done <= '0';
	case y is
		when S1 => 
			sclrP <= '1'; EP <= '1';
			if s = '1' then
				L <= '1'; E <= '1';
			end if;
		when S2 =>
			E <= '1';
			if z = '0' then
				if B(0) = '1' then EP <= '1'; end if;
			end if;
		when S3 =>
			done <= '1';
	end case;
	end process;
end Behavioral;

vhdl-designs/seq/mult/tb_multiplier.vhd
library ieee;
use ieee.std_logic_1164.ALL;
use ieee.std_logic_arith.all;
use std.env.finish;
 
entity tb_multiplier is
	generic (N: INTEGER := 4);
end tb_multiplier;
 
architecture behavior of tb_multiplier is 
   --Inputs
   signal clk: std_logic := '0';
   signal reset: std_logic := '0';
   signal s: std_logic := '0';
   signal dA: std_logic_vector (N-1 downto 0) := (others => '0');
   signal dB: std_logic_vector (N-1 downto 0) := (others => '0');

 	--Outputs
   signal P: std_logic_vector (2*N - 1 downto 0);
   signal done: std_logic;

   -- Clock period definitions
   constant clock_period: time := 10 ns;
begin
	-- Instantiate the Unit Under Test (UUT)
  uut: entity work.multiplier port map (clk, reset, s, dA, dB, P, done);

  -- Clock process definitions
  clock_process: process
  begin
  clk <= '0'; 
    wait for clock_period/2;
  clk <= '1'; 
    wait for clock_period/2;
  end process;

  -- Stimulus process
  stimulus: process
  begin		
    -- hold reset state for 100 ns.
    wait for 100 ns; reset <= '1';

    dA <= conv_std_logic_vector (13, N); -- "1101";
    dB <= conv_std_logic_vector (11, N); -- "1011";
    s <= '1'; wait for clock_period;
    s <= '0';
    wait for clock_period*(N+3); -- Multiplication takes at most N + 1 cycles
    
    dA <= conv_std_logic_vector (9, N);    -- "1001";
    dB <= conv_std_logic_vector (15, N);   -- "1111";
    s <= '1'; wait for clock_period;
    s <= '0';
    wait for clock_period*(N+3);
    finish;
  end process;
end architecture;

vhdl-designs/seq/mult/tb_multiplier.vcd
$date
  Mon Jan 15 03:43:46 2024
$end
$version
  GHDL v0
$end
$timescale
  1 fs
$end
$scope module standard $end
$upscope $end
$scope module textio $end
$upscope $end
$scope module std_logic_1164 $end
$upscope $end
$scope module std_logic_arith $end
$upscope $end
$scope module env $end
$upscope $end
$scope module tb_multiplier $end
$var reg 1 ! clk $end
$var reg 1 " reset $end
$var reg 1 # s $end
$var reg 4 $ da[3:0] $end
$var reg 4 % db[3:0] $end
$var reg 8 & p[7:0] $end
$var reg 1 ' done $end
$scope module uut $end
$var reg 1 ( clk $end
$var reg 1 ) reset $end
$var reg 1 * s $end
$var reg 4 + da[3:0] $end
$var reg 4 , db[3:0] $end
$var reg 8 - p[7:0] $end
$var reg 1 . done $end
$comment y is not handled $end
$var reg 1 / l $end
$var reg 1 0 e $end
$var reg 1 1 ep $end
$var reg 1 2 sclrp $end
$var reg 1 3 z $end
$var reg 4 4 b[3:0] $end
$var reg 8 5 a[7:0] $end
$var reg 8 6 dax[7:0] $end
$var reg 8 7 dp[7:0] $end
$var reg 8 8 pt[7:0] $end
$scope module ra $end
$var reg 1 9 clk $end
$var reg 1 : reset $end
$var reg 1 ; din $end
$var reg 1 < e $end
$var reg 1 = s_l $end
$var reg 8 > d[7:0] $end
$var reg 8 ? q[7:0] $end
$var reg 1 @ shift_out $end
$var reg 8 A qt[7:0] $end
$scope module gl $end
$upscope $end
$upscope $end
$scope module rb $end
$var reg 1 B clk $end
$var reg 1 C reset $end
$var reg 1 D din $end
$var reg 1 E e $end
$var reg 1 F s_l $end
$var reg 4 G d[3:0] $end
$var reg 4 H q[3:0] $end
$var reg 1 I shift_out $end
$var reg 4 J qt[3:0] $end
$scope module gr $end
$upscope $end
$upscope $end
$scope module ga $end
$var reg 1 K addsub $end
$var reg 8 L x[7:0] $end
$var reg 8 M y[7:0] $end
$var reg 8 N s[7:0] $end
$var reg 1 O overflow $end
$var reg 1 P cout $end
$var reg 9 Q c[8:0] $end
$var reg 8 R yx[7:0] $end
$scope module gi(0) $end
$scope module fi $end
$var reg 1 S x_in $end
$var reg 1 T y_in $end
$var reg 1 U c_in $end
$var reg 1 V s_out $end
$var reg 1 W c_out $end
$upscope $end
$upscope $end
$scope module gi(1) $end
$scope module fi $end
$var reg 1 X x_in $end
$var reg 1 Y y_in $end
$var reg 1 Z c_in $end
$var reg 1 [ s_out $end
$var reg 1 \ c_out $end
$upscope $end
$upscope $end
$scope module gi(2) $end
$scope module fi $end
$var reg 1 ] x_in $end
$var reg 1 ^ y_in $end
$var reg 1 _ c_in $end
$var reg 1 ` s_out $end
$var reg 1 a c_out $end
$upscope $end
$upscope $end
$scope module gi(3) $end
$scope module fi $end
$var reg 1 b x_in $end
$var reg 1 c y_in $end
$var reg 1 d c_in $end
$var reg 1 e s_out $end
$var reg 1 f c_out $end
$upscope $end
$upscope $end
$scope module gi(4) $end
$scope module fi $end
$var reg 1 g x_in $end
$var reg 1 h y_in $end
$var reg 1 i c_in $end
$var reg 1 j s_out $end
$var reg 1 k c_out $end
$upscope $end
$upscope $end
$scope module gi(5) $end
$scope module fi $end
$var reg 1 l x_in $end
$var reg 1 m y_in $end
$var reg 1 n c_in $end
$var reg 1 o s_out $end
$var reg 1 p c_out $end
$upscope $end
$upscope $end
$scope module gi(6) $end
$scope module fi $end
$var reg 1 q x_in $end
$var reg 1 r y_in $end
$var reg 1 s c_in $end
$var reg 1 t s_out $end
$var reg 1 u c_out $end
$upscope $end
$upscope $end
$scope module gi(7) $end
$scope module fi $end
$var reg 1 v x_in $end
$var reg 1 w y_in $end
$var reg 1 x c_in $end
$var reg 1 y s_out $end
$var reg 1 z c_out $end
$upscope $end
$upscope $end
$upscope $end
$scope module rp $end
$var reg 1 { clk $end
$var reg 1 | reset $end
$var reg 1 } e $end
$var reg 1 !" clear $end
$var reg 8 "" d[7:0] $end
$var reg 8 #" q[7:0] $end
$var reg 8 $" qt[7:0] $end
$upscope $end
$upscope $end
$upscope $end
$enddefinitions $end
#0
0!
0"
0#
b0000 $
b0000 %
b00000000 &
0'
0(
0)
0*
b0000 +
b0000 ,
b00000000 -
0.
0/
00
11
12
13
b0000 4
b00000000 5
b00000000 6
b00000000 7
b00000000 8
09
0:
0;
0<
0=
b00000000 >
b00000000 ?
0@
b00000000 A
0B
0C
0D
0E
0F
b0000 G
b0000 H
0I
b0000 J
0K
b00000000 L
b00000000 M
b00000000 N
0O
0P
b000000000 Q
b00000000 R
0S
0T
0U
0V
0W
0X
0Y
0Z
0[
0\
0]
0^
0_
0`
0a
0b
0c
0d
0e
0f
0g
0h
0i
0j
0k
0l
0m
0n
0o
0p
0q
0r
0s
0t
0u
0v
0w
0x
0y
0z
0{
0|
1}
1!"
b00000000 ""
b00000000 #"
b00000000 $"
#5000000
1!
1(
19
1B
1{
#10000000
0!
0(
09
0B
0{
#15000000
1!
1(
19
1B
1{
#20000000
0!
0(
09
0B
0{
#25000000
1!
1(
19
1B
1{
#30000000
0!
0(
09
0B
0{
#35000000
1!
1(
19
1B
1{
#40000000
0!
0(
09
0B
0{
#45000000
1!
1(
19
1B
1{
#50000000
0!
0(
09
0B
0{
#55000000
1!
1(
19
1B
1{
#60000000
0!
0(
09
0B
0{
#65000000
1!
1(
19
1B
1{
#70000000
0!
0(
09
0B
0{
#75000000
1!
1(
19
1B
1{
#80000000
0!
0(
09
0B
0{
#85000000
1!
1(
19
1B
1{
#90000000
0!
0(
09
0B
0{
#95000000
1!
1(
19
1B
1{
#100000000
0!
1"
1#
b1101 $
b1011 %
0(
1)
1*
b1101 +
b1011 ,
1/
10
b00001101 6
09
1:
1<
1=
b00001101 >
0B
1C
1E
1F
b1011 G
0{
1|
#105000000
1!
1(
0/
11
02
03
b1011 4
b00001101 5
b00001101 7
19
0=
b00001101 ?
b00001101 A
1B
0F
b1011 H
1I
b1011 J
b00001101 L
b00001101 N
1S
1V
1]
1`
1b
1e
1{
1}
0!"
b00001101 ""
#110000000
0!
0#
0(
0*
09
0B
0{
#115000000
1!
b00001101 &
1(
b00001101 -
b0101 4
b00011010 5
b00100111 7
b00001101 8
19
b00011010 ?
b00011010 A
1B
b0101 H
b0101 J
b00011010 L
b00001101 M
b00100111 N
b000110000 Q
b00001101 R
0S
1T
1V
1X
1[
0]
1^
1`
1c
0e
1f
1g
1i
0j
1k
1n
1o
1{
b00100111 ""
b00001101 #"
b00001101 $"
#120000000
0!
0(
09
0B
0{
#125000000
1!
b00100111 &
1(
b00100111 -
01
b0010 4
b00110100 5
b01011011 7
b00100111 8
19
b00110100 ?
b00110100 A
1B
b0010 H
0I
b0010 J
b00110100 L
b00100111 M
b01011011 N
b001001000 Q
b00100111 R
0X
1Y
1[
1]
0`
1a
0b
0c
1d
1e
0f
0i
1j
0k
1l
1m
0n
0o
1p
1s
1t
1{
0}
b01011011 ""
b00100111 #"
b00100111 $"
#130000000
0!
0(
09
0B
0{
#135000000
1!
1(
11
b0001 4
b01101000 5
b10001111 7
19
b01101000 ?
b01101000 A
1B
b0001 H
1I
b0001 J
b01101000 L
b10001111 N
1O
b011000000 Q
0]
1`
0a
1b
0d
1e
0f
0g
0i
0j
1q
0t
1u
1x
1y
1{
1}
b10001111 ""
#140000000
0!
0(
09
0B
0{
#145000000
1!
b10001111 &
1(
b10001111 -
01
13
b0000 4
b11010000 5
b01011111 7
b10001111 8
19
b11010000 ?
1@
b11010000 A
1B
b0000 H
0I
b0000 J
b11010000 L
b10001111 M
b01011111 N
1O
1P
b100000000 Q
b10001111 R
0b
1c
1e
1g
1j
0l
0m
0o
0p
0s
1t
0u
1v
1w
0x
0y
1z
1{
0}
b01011111 ""
b10001111 #"
b10001111 $"
#150000000
0!
0(
09
0B
0{
#155000000
1!
1'
1(
1.
00
b10100000 5
b00101111 7
19
0<
b10100000 ?
b10100000 A
1B
0E
b10100000 L
b00101111 N
0g
0j
1l
1o
0q
0t
1{
b00101111 ""
#160000000
0!
0(
09
0B
0{
#165000000
1!
0'
1(
0.
11
12
19
1B
1{
1}
1!"
#170000000
0!
0(
09
0B
0{
#175000000
1!
b00000000 &
1(
b00000000 -
b10100000 7
b00000000 8
19
1B
b00000000 M
b10100000 N
0O
0P
b000000000 Q
b00000000 R
0T
0V
0Y
0[
0^
0`
0c
0e
0w
1y
0z
1{
b10100000 ""
b00000000 #"
b00000000 $"
#180000000
0!
1#
b1001 $
b1111 %
0(
1*
b1001 +
b1111 ,
1/
10
b00001001 6
09
1<
1=
b00001001 >
0B
1E
1F
b1111 G
0{
#185000000
1!
1(
0/
11
02
03
b1111 4
b00001001 5
b00001001 7
19
0=
b00001001 ?
0@
b00001001 A
1B
0F
b1111 H
1I
b1111 J
b00001001 L
b00001001 N
1S
1V
1b
1e
0l
0o
0v
0y
1{
1}
0!"
b00001001 ""
#190000000
0!
0#
0(
0*
09
0B
0{
#195000000
1!
b00001001 &
1(
b00001001 -
b0111 4
b00010010 5
b00011011 7
b00001001 8
19
b00010010 ?
b00010010 A
1B
b0111 H
b0111 J
b00010010 L
b00001001 M
b00011011 N
b00001001 R
0S
1T
1V
1X
1[
0b
1c
1e
1g
1j
1{
b00011011 ""
b00001001 #"
b00001001 $"
#200000000
0!
0(
09
0B
0{
#205000000
1!
b00011011 &
1(
b00011011 -
b0011 4
b00100100 5
b00111111 7
b00011011 8
19
b00100100 ?
b00100100 A
1B
b0011 H
b0011 J
b00100100 L
b00011011 M
b00111111 N
b00011011 R
0X
1Y
1[
1]
1`
0g
1h
1j
1l
1o
1{
b00111111 ""
b00011011 #"
b00011011 $"
#210000000
0!
0(
09
0B
0{
#215000000
1!
b00111111 &
1(
b00111111 -
b0001 4
b01001000 5
b10000111 7
b00111111 8
19
b01001000 ?
b01001000 A
1B
b0001 H
b0001 J
b01001000 L
b00111111 M
b10000111 N
1O
b011110000 Q
b00111111 R
0]
1^
1`
1b
0e
1f
1i
0j
1k
0l
1m
1n
0o
1p
1q
1s
0t
1u
1x
1y
1{
b10000111 ""
b00111111 #"
b00111111 $"
#220000000
0!
0(
09
0B
0{
#225000000
1!
b10000111 &
1(
b10000111 -
01
13
b0000 4
b10010000 5
b00010111 7
b10000111 8
19
b10010000 ?
1@
b10010000 A
1B
b0000 H
0I
b0000 J
b10010000 L
b10000111 M
b00010111 N
1P
b100000000 Q
b10000111 R
0b
0c
0e
0f
1g
0h
0i
1j
0k
0m
0n
0o
0p
0q
0s
0t
0u
1v
1w
0x
0y
1z
1{
0}
b00010111 ""
b10000111 #"
b10000111 $"
#230000000
0!
0(
09
0B
0{
#235000000
1!
1'
1(
1.
00
b00100000 5
b10100111 7
19
0<
b00100000 ?
0@
b00100000 A
1B
0E
b00100000 L
b10100111 N
0O
0P
b000000000 Q
0g
0j
1l
1o
0v
1y
0z
1{
b10100111 ""
#240000000
0!
0(
09
0B
0{
#245000000
1!
0'
1(
0.
11
12
19
1B
1{
1}
1!"
#250000000
0!
0(
09
0B
0{
#255000000
1!
b00000000 &
1(
b00000000 -
b00100000 7
b00000000 8
19
1B
b00000000 M
b00100000 N
b00000000 R
0T
0V
0Y
0[
0^
0`
0w
0y
1{
b00100000 ""
b00000000 #"
b00000000 $"
