vhdl files/comb/mux/mux_4to1.vhd
library ieee;
use ieee.std_logic_1164.all;

entity mux_4to1 is
  port (
    ABCD_in : in  std_logic_vector(3 downto 0);
    Sel_in  : in  std_logic_vector(1 downto 0);
    Q_out   : out std_logic
  );
end entity;

architecture behavior of mux_4to1 is
begin
  DUT: process(ABCD_in, Sel_in)
  begin
    case Sel_in is
      when "00"   => Q_out <= ABCD_in(0);
      when "01"   => Q_out <= ABCD_in(1);
      when "10"   => Q_out <= ABCD_in(2);
      when "11"   => Q_out <= ABCD_in(3);
      when others => Q_out <= 'X';
    end case;
  end process;
end architecture;

vhdl files/comb/mux/tb_mux_4to1.vhd
library ieee;
use ieee.std_logic_1164.all;
use ieee.std_logic_textio.all;

library STD;
use STD.textio.all;

entity tb_mux_4to1 is
end entity;

architecture bench of tb_mux_4to1 is

  component mux_4to1
    port (
      ABCD_in: in std_logic_vector(3 downto 0);
      Sel_in: in std_logic_vector(1 downto 0);
      Q_out: out std_logic
    );
  end component;

  signal ACBD_tb_in: std_logic_vector(3 downto 0);
  signal Sel_tb_in: std_logic_vector(1 downto 0);
  signal Q_tb_in: std_logic;

begin
  DUT: mux_4to1 port map(ABCD_in => ACBD_tb_in, Sel_in => Sel_tb_in, Q_out => Q_tb_in);
  process
    file Fin : text open read_mode is "mux_4to1_tests.txt";

    variable current_read_line   : line;
    variable current_read_field1 : std_logic_vector(0 to 3);
    variable current_read_field2 : std_logic_vector(0 to 1);
    variable current_read_field3 : std_logic;

  begin
    while (not endFile(Fin)) loop

      readline(Fin, current_read_line);
      read(current_read_line, current_read_field1);
      read(current_read_line, current_read_field2);
      read(current_read_line, current_read_field3);

      ACBD_tb_in <= current_read_field1;
      Sel_tb_in  <= current_read_field2;
      wait for 50 ns;

      assert(Q_tb_in = current_read_field3);

    end loop;
    wait;
  end process;
end architecture;

vhdl files/comb/mux/tb_mux_4to1.vcd
$date
  Mon Jan 15 03:16:10 2024
$end
$version
  GHDL v0
$end
$timescale
  1 fs
$end
$scope module standard $end
$upscope $end
$scope module textio $end
$upscope $end
$scope module std_logic_1164 $end
$upscope $end
$scope module std_logic_textio $end
$upscope $end
$scope module tb_mux_4to1 $end
$var reg 4 ! acbd_tb_in[3:0] $end
$var reg 2 " sel_tb_in[1:0] $end
$var reg 1 # q_tb_in $end
$scope module dut $end
$var reg 4 $ abcd_in[3:0] $end
$var reg 2 % sel_in[1:0] $end
$var reg 1 & q_out $end
$upscope $end
$upscope $end
$enddefinitions $end
#0
b1000 !
b00 "
0#
b1000 $
b00 %
0&
#50000000
b01 "
b01 %
#100000000
b10 "
b10 %
#150000000
b11 "
1#
b11 %
1&
#200000000
b1101 !
b00 "
b1101 $
b00 %
#250000000
b01 "
0#
b01 %
0&
#300000000
b10 "
1#
b10 %
1&
#350000000
b11 "
b11 %
#400000000
b0111 !
b00 "
b0111 $
b00 %
#450000000
b01 "
b01 %
#500000000
b10 "
b10 %
#550000000
b11 "
0#
b11 %
0&
#600000000
b1010 !
b00 "
b1010 $
b00 %
#650000000
b01 "
1#
b01 %
1&
#700000000
b10 "
0#
b10 %
0&
#750000000
b11 "
1#
b11 %
1&
#800000000
b0101 !
b00 "
b0101 $
b00 %
#850000000
b01 "
0#
b01 %
0&
#900000000
b10 "
1#
b10 %
1&
#950000000
b11 "
0#
b11 %
0&
